odoo/addons/stock_measuring_device/README.rst
odoo/addons/stock_measuring_device/__init__.py
odoo/addons/stock_measuring_device/__manifest__.py
odoo/addons/stock_measuring_device/components/__init__.py
odoo/addons/stock_measuring_device/components/measuring_device_component.py
odoo/addons/stock_measuring_device/data/uom.xml
odoo/addons/stock_measuring_device/i18n/stock_measuring_device.pot
odoo/addons/stock_measuring_device/models/__init__.py
odoo/addons/stock_measuring_device/models/measuring_device.py
odoo/addons/stock_measuring_device/models/product_packaging.py
odoo/addons/stock_measuring_device/models/stock_warehouse.py
odoo/addons/stock_measuring_device/readme/CONFIGURE.rst
odoo/addons/stock_measuring_device/readme/CONTRIBUTORS.rst
odoo/addons/stock_measuring_device/readme/CREDITS.rst
odoo/addons/stock_measuring_device/readme/DESCRIPTION.rst
odoo/addons/stock_measuring_device/readme/INSTALL.rst
odoo/addons/stock_measuring_device/readme/ROADMAP.rst
odoo/addons/stock_measuring_device/readme/USAGE.rst
odoo/addons/stock_measuring_device/security/ir.model.access.csv
odoo/addons/stock_measuring_device/static/description/icon.png
odoo/addons/stock_measuring_device/static/description/index.html
odoo/addons/stock_measuring_device/static/src/js/measuring_wizard.js
odoo/addons/stock_measuring_device/static/src/scss/measuring_wizard.scss
odoo/addons/stock_measuring_device/views/assets.xml
odoo/addons/stock_measuring_device/views/measuring_device_view.xml
odoo/addons/stock_measuring_device/views/menu.xml
odoo/addons/stock_measuring_device/wizard/__init__.py
odoo/addons/stock_measuring_device/wizard/measuring_wizard.py
odoo/addons/stock_measuring_device/wizard/measuring_wizard.xml
odoo/addons/stock_measuring_device/wizard/measuring_wizard_line.py
odoo14_addon_stock_measuring_device-14.0.1.0.1.dist-info/METADATA
odoo14_addon_stock_measuring_device-14.0.1.0.1.dist-info/WHEEL
odoo14_addon_stock_measuring_device-14.0.1.0.1.dist-info/top_level.txt
odoo14_addon_stock_measuring_device-14.0.1.0.1.dist-info/RECORD
