Metadata-Version: 2.1
Name: odoo14-addon-stock-measuring-device
Version: 14.0.1.0.1
Summary: Implement a common interface for measuring and weighing devices
Home-page: https://github.com/OCA/stock-logistics-warehouse
Author: Camptocamp, Odoo Community Association (OCA)
Author-email: support@odoo-community.org
License: AGPL-3
Platform: UNKNOWN
Classifier: Programming Language :: Python
Classifier: Framework :: Odoo
Classifier: Framework :: Odoo :: 14.0
Classifier: License :: OSI Approved :: GNU Affero General Public License v3
Classifier: Development Status :: 3 - Alpha
Requires-Python: >=3.6
Requires-Dist: odoo14-addon-component
Requires-Dist: odoo14-addon-product-dimension
Requires-Dist: odoo14-addon-product-packaging-dimension
Requires-Dist: odoo14-addon-product-packaging-type-required
Requires-Dist: odoo14-addon-web-ir-actions-act-view-reload
Requires-Dist: odoo14-addon-web-notify
Requires-Dist: odoo14-addon-web-tree-dynamic-colored-field
Requires-Dist: odoo (<14.1dev,>=14.0a)
